{
    "creeper3-00000.png": {
        "Creeper": [
            [
                156,
                163,
                196,
                90
            ]
        ],
        "Pig": [],
        "purge": false,
        "written": true
    },
    "creeper3-00001.png": {
        "Creeper": [
            [
                69,
                175,
                129,
                89
            ]
        ],
        "Pig": [],
        "purge": false,
        "written": true
    },
    "creeper3-00002.png": {
        "Creeper": [
            [
                136,
                174,
                192,
                94
            ]
        ],
        "Pig": [],
        "purge": false,
        "written": true
    },
    "creeper3-00003.png": {
        "Creeper": [
            [
                164,
                194,
                202,
                107
            ]
        ],
        "Pig": [],
        "purge": false,
        "written": true
    },
    "creeper3-00004.png": {
        "Creeper": [
            [
                292,
                156,
                387,
                236
            ]
        ],
        "Pig": [],
        "purge": false,
        "written": true
    },
    "creeper3-00005.png": {
        "Creeper": [
            [
                205,
                147,
                241,
                69
            ]
        ],
        "Pig": [],
        "purge": false,
        "written": true
    },
    "creeper3-00006.png": {
        "Creeper": [
            [
                190,
                127,
                213,
                80
            ]
        ],
        "Pig": [],
        "purge": false,
        "written": true
    },
    "creeper3-00007.png": {
        "Creeper": [
            [
                152,
                125,
                176,
                87
            ]
        ],
        "Pig": [],
        "purge": false,
        "written": true
    },
    "creeper3-00008.png": {
        "Creeper": [
            [
                199,
                101,
                212,
                118
            ]
        ],
        "Pig": [],
        "purge": false,
        "written": true
    },
    "creeper3-00009.png": {
        "Creeper": [
            [
                225,
                98,
                241,
                126
            ]
        ],
        "Pig": [],
        "purge": false,
        "written": true
    },
    "creeper3-00010.png": {
        "Creeper": [
            [
                220,
                100,
                239,
                129
            ]
        ],
        "Pig": [],
        "purge": false,
        "written": true
    },
    "creeper3-00011.png": {
        "Creeper": [],
        "Pig": [],
        "purge": false,
        "written": false
    },
    "creeper3-00012.png": {
        "Creeper": [
            [
                73,
                204,
                94,
                172
            ]
        ],
        "Pig": [],
        "purge": false,
        "written": true
    },
    "creeper3-00013.png": {
        "Creeper": [
            [
                201,
                97,
                216,
                70
            ]
        ],
        "Pig": [],
        "purge": false,
        "written": true
    },
    "creeper3-00014.png": {
        "Creeper": [
            [
                243,
                41,
                260,
                8
            ]
        ],
        "Pig": [],
        "purge": false,
        "written": true
    },
    "creeper3-00015.png": {
        "Creeper": [
            [
                361,
                54,
                400,
                9
            ]
        ],
        "Pig": [],
        "purge": false,
        "written": true
    },
    "creeper3-00016.png": {
        "Creeper": [
            [
                361,
                76,
                394,
                128
            ]
        ],
        "Pig": [],
        "purge": false,
        "written": true
    },
    "creeper3-00017.png": {
        "Creeper": [
            [
                347,
                165,
                391,
                227
            ]
        ],
        "Pig": [],
        "purge": false,
        "written": true
    },
    "creeper3-00018.png": {
        "Creeper": [
            [
                241,
                121,
                298,
                235
            ]
        ],
        "Pig": [],
        "purge": false,
        "written": true
    },
    "creeper3-00019.png": {
        "Creeper": [
            [
                163,
                40,
                229,
                167
            ]
        ],
        "Pig": [],
        "purge": false,
        "written": true
    },
    "creeper3-00020.png": {
        "Creeper": [
            [
                188,
                114,
                217,
                53
            ]
        ],
        "Pig": [],
        "purge": false,
        "written": true
    },
    "creeper3-00021.png": {
        "Creeper": [
            [
                106,
                100,
                128,
                53
            ]
        ],
        "Pig": [],
        "purge": false,
        "written": true
    },
    "creeper3-00022.png": {
        "Creeper": [
            [
                3,
                2,
                50,
                53
            ]
        ],
        "Pig": [],
        "purge": false,
        "written": true
    },
    "creeper3-00023.png": {
        "Creeper": [
            [
                19,
                117,
                45,
                155
            ]
        ],
        "Pig": [],
        "purge": false,
        "written": true
    },
    "creeper3-00024.png": {
        "Creeper": [
            [
                72,
                118,
                93,
                150
            ]
        ],
        "Pig": [],
        "purge": false,
        "written": true
    },
    "creeper3-00025.png": {
        "Creeper": [
            [
                17,
                215,
                52,
                164
            ]
        ],
        "Pig": [],
        "purge": false,
        "written": true
    },
    "creeper3-00026.png": {
        "Creeper": [
            [
                193,
                193,
                216,
                152
            ]
        ],
        "Pig": [],
        "purge": false,
        "written": true
    },
    "creeper3-00027.png": {
        "Creeper": [
            [
                359,
                184,
                402,
                235
            ]
        ],
        "Pig": [],
        "purge": false,
        "written": true
    },
    "creeper3-00028.png": {
        "Creeper": [
            [
                381,
                157,
                422,
                207
            ]
        ],
        "Pig": [],
        "purge": false,
        "written": true
    },
    "creeper3-00029.png": {
        "Creeper": [
            [
                367,
                81,
                399,
                39
            ]
        ],
        "Pig": [],
        "purge": false,
        "written": true
    },
    "creeper3-00030.png": {
        "Creeper": [
            [
                204,
                74,
                220,
                105
            ]
        ],
        "Pig": [],
        "purge": false,
        "written": true
    },
    "creeper3-00031.png": {
        "Creeper": [
            [
                178,
                77,
                201,
                113
            ]
        ],
        "Pig": [],
        "purge": false,
        "written": true
    },
    "creeper3-00032.png": {
        "Creeper": [
            [
                187,
                104,
                202,
                81
            ]
        ],
        "Pig": [],
        "purge": false,
        "written": true
    },
    "creeper3-00033.png": {
        "Creeper": [
            [
                183,
                104,
                199,
                80
            ]
        ],
        "Pig": [],
        "purge": false,
        "written": true
    },
    "creeper3-00034.png": {
        "Creeper": [
            [
                186,
                108,
                203,
                74
            ]
        ],
        "Pig": [],
        "purge": false,
        "written": true
    },
    "creeper3-00035.png": {
        "Creeper": [
            [
                197,
                129,
                214,
                92
            ]
        ],
        "Pig": [],
        "purge": false,
        "written": true
    },
    "creeper3-00036.png": {
        "Creeper": [
            [
                182,
                108,
                211,
                159
            ]
        ],
        "Pig": [],
        "purge": false,
        "written": true
    },
    "creeper3-00037.png": {
        "Creeper": [
            [
                191,
                88,
                235,
                163
            ]
        ],
        "Pig": [],
        "purge": false,
        "written": true
    },
    "creeper3-00038.png": {
        "Creeper": [
            [
                203,
                69,
                258,
                194
            ]
        ],
        "Pig": [],
        "purge": false,
        "written": true
    },
    "creeper3-00039.png": {
        "Creeper": [
            [
                151,
                105,
                193,
                180
            ]
        ],
        "Pig": [],
        "purge": false,
        "written": true
    },
    "creeper3-00040.png": {
        "Creeper": [
            [
                195,
                81,
                223,
                136
            ]
        ],
        "Pig": [],
        "purge": false,
        "written": true
    },
    "creeper3-00041.png": {
        "Creeper": [],
        "Pig": [],
        "purge": false,
        "written": false
    },
    "creeper3-00042.png": {
        "Creeper": [
            [
                206,
                128,
                224,
                91
            ]
        ],
        "Pig": [],
        "purge": false,
        "written": true
    },
    "creeper3-00043.png": {
        "Creeper": [
            [
                207,
                92,
                227,
                129
            ]
        ],
        "Pig": [],
        "purge": false,
        "written": true
    },
    "creeper3-00044.png": {
        "Creeper": [
            [
                179,
                95,
                201,
                139
            ]
        ],
        "Pig": [],
        "purge": false,
        "written": true
    },
    "creeper3-00045.png": {
        "Creeper": [
            [
                197,
                121,
                220,
                81
            ]
        ],
        "Pig": [],
        "purge": false,
        "written": true
    },
    "creeper3-00046.png": {
        "Creeper": [
            [
                208,
                101,
                225,
                135
            ]
        ],
        "Pig": [],
        "purge": false,
        "written": true
    },
    "creeper3-00047.png": {
        "Creeper": [
            [
                215,
                123,
                229,
                146
            ]
        ],
        "Pig": [],
        "purge": false,
        "written": true
    },
    "creeper3-00048.png": {
        "Creeper": [
            [
                214,
                122,
                227,
                139
            ]
        ],
        "Pig": [],
        "purge": false,
        "written": true
    },
    "creeper3-00049.png": {
        "Creeper": [],
        "Pig": [],
        "purge": false,
        "written": false
    },
    "creeper3-00050.png": {
        "Creeper": [],
        "Pig": [],
        "purge": false,
        "written": false
    },
    "creeper3-00051.png": {
        "Creeper": [],
        "Pig": [],
        "purge": false,
        "written": false
    },
    "creeper3-00052.png": {
        "Creeper": [
            [
                210,
                129,
                228,
                90
            ]
        ],
        "Pig": [],
        "purge": false,
        "written": true
    },
    "creeper3-00053.png": {
        "Creeper": [
            [
                225,
                173,
                250,
                122
            ]
        ],
        "Pig": [],
        "purge": false,
        "written": true
    },
    "creeper3-00054.png": {
        "Creeper": [
            [
                239,
                121,
                272,
                58
            ]
        ],
        "Pig": [],
        "purge": false,
        "written": true
    },
    "creeper3-00055.png": {
        "Creeper": [
            [
                120,
                110,
                6,
                0
            ]
        ],
        "Pig": [],
        "purge": false,
        "written": true
    },
    "creeper3-00056.png": {
        "Creeper": [
            [
                247,
                57,
                287,
                147
            ]
        ],
        "Pig": [],
        "purge": false,
        "written": true
    },
    "creeper3-00057.png": {
        "Creeper": [
            [
                311,
                109,
                400,
                237
            ]
        ],
        "Pig": [],
        "purge": false,
        "written": true
    },
    "creeper3-00058.png": {
        "Creeper": [
            [
                345,
                103,
                423,
                228
            ]
        ],
        "Pig": [],
        "purge": false,
        "written": true
    },
    "creeper3-00059.png": {
        "Creeper": [
            [
                220,
                93,
                255,
                159
            ]
        ],
        "Pig": [],
        "purge": false,
        "written": true
    },
    "creeper3-00060.png": {
        "Creeper": [],
        "Pig": [],
        "purge": false,
        "written": false
    },
    "creeper3-00061.png": {
        "Creeper": [
            [
                4,
                79,
                58,
                134
            ]
        ],
        "Pig": [],
        "purge": false,
        "written": true
    },
    "creeper3-00062.png": {
        "Creeper": [
            [
                202,
                101,
                224,
                138
            ]
        ],
        "Pig": [],
        "purge": false,
        "written": true
    },
    "creeper3-00063.png": {
        "Creeper": [],
        "Pig": [],
        "purge": false,
        "written": false
    },
    "creeper3-00064.png": {
        "Creeper": [
            [
                148,
                114,
                165,
                136
            ]
        ],
        "Pig": [],
        "purge": false,
        "written": true
    },
    "creeper3-00065.png": {
        "Creeper": [
            [
                270,
                93,
                290,
                127
            ]
        ],
        "Pig": [],
        "purge": false,
        "written": true
    },
    "creeper3-00066.png": {
        "Creeper": [
            [
                265,
                88,
                284,
                121
            ]
        ],
        "Pig": [],
        "purge": false,
        "written": true
    },
    "creeper3-00067.png": {
        "Creeper": [
            [
                246,
                104,
                266,
                132
            ]
        ],
        "Pig": [],
        "purge": false,
        "written": true
    },
    "creeper3-00068.png": {
        "Creeper": [
            [
                237,
                103,
                251,
                129
            ]
        ],
        "Pig": [],
        "purge": false,
        "written": true
    },
    "creeper3-00069.png": {
        "Creeper": [],
        "Pig": [],
        "purge": false,
        "written": false
    },
    "creeper3-00070.png": {
        "Creeper": [
            [
                199,
                110,
                218,
                132
            ]
        ],
        "Pig": [],
        "purge": false,
        "written": true
    },
    "creeper3-00071.png": {
        "Creeper": [
            [
                189,
                108,
                214,
                157
            ]
        ],
        "Pig": [],
        "purge": false,
        "written": true
    },
    "creeper3-00072.png": {
        "Creeper": [
            [
                12,
                114,
                80,
                218
            ]
        ],
        "Pig": [],
        "purge": false,
        "written": true
    },
    "creeper3-00073.png": {
        "Creeper": [
            [
                116,
                43,
                164,
                119
            ]
        ],
        "Pig": [],
        "purge": false,
        "written": true
    },
    "creeper3-00074.png": {
        "Creeper": [
            [
                110,
                18,
                153,
                81
            ]
        ],
        "Pig": [],
        "purge": false,
        "written": true
    },
    "creeper3-00075.png": {
        "Creeper": [
            [
                296,
                96,
                323,
                56
            ]
        ],
        "Pig": [],
        "purge": false,
        "written": true
    },
    "creeper3-00076.png": {
        "Creeper": [
            [
                348,
                61,
                390,
                14
            ]
        ],
        "Pig": [],
        "purge": false,
        "written": true
    },
    "creeper3-00077.png": {
        "Creeper": [
            [
                138,
                55,
                162,
                90
            ]
        ],
        "Pig": [],
        "purge": false,
        "written": true
    },
    "creeper3-00078.png": {
        "Creeper": [
            [
                105,
                121,
                126,
                166
            ]
        ],
        "Pig": [],
        "purge": false,
        "written": true
    },
    "creeper3-00079.png": {
        "Creeper": [
            [
                88,
                150,
                117,
                110
            ]
        ],
        "Pig": [],
        "purge": false,
        "written": true
    }
}